[
  {
    "imgFileName": "exploration-lab-sample-img.png",
    "imgLocation": "Exploration Lab",
    "imgComment": "Add a small comment"
  },
  {
    "imgFileName": "exploration-lab-sample-img.png",
    "imgLocation": "Exploration Lab",
    "imgComment": "Add a small comment"
  },
  {
    "imgFileName": "exploration-lab-sample-img.png",
    "imgLocation": "Exploration Lab",
    "imgComment": "Add a small comment"
  },
  {
    "imgFileName": "exploration-lab-sample-img.png",
    "imgLocation": "Exploration Lab",
    "imgComment": "Add a small comment"
  },
  {
    "imgFileName": "exploration-lab-sample-img.png",
    "imgLocation": "Exploration Lab",
    "imgComment": "Add a small comment"
  },
  {
    "imgFileName": "exploration-lab-sample-img.png",
    "imgLocation": "Exploration Lab",
    "imgComment": "Add a small comment"
  },
  {
    "imgFileName": "exploration-lab-sample-img.png",
    "imgLocation": "Exploration Lab",
    "imgComment": "Add a small comment"
  },
  {
    "imgFileName": "exploration-lab-sample-img.png",
    "imgLocation": "Exploration Lab",
    "imgComment": "Add a small comment"
  },
  {
    "imgFileName": "exploration-lab-sample-img.png",
    "imgLocation": "Exploration Lab",
    "imgComment": "Add a small comment"
  }
]