[
  {
    "imgFileName": "math-lab-sample-img.png",
    "imgLocation": "Math Lab",
    "imgComment": "Add a small comment"
  },
  {
    "imgFileName": "math-lab-sample-img.png",
    "imgLocation": "Math Lab",
    "imgComment": "Add a small comment"
  },
  {
    "imgFileName": "math-lab-sample-img.png",
    "imgLocation": "Math Lab",
    "imgComment": "Add a small comment"
  },
  {
    "imgFileName": "math-lab-sample-img.png",
    "imgLocation": "Math Lab",
    "imgComment": "Add a small comment"
  },
  {
    "imgFileName": "math-lab-sample-img.png",
    "imgLocation": "Math Lab",
    "imgComment": "Add a small comment"
  },
  {
    "imgFileName": "math-lab-sample-img.png",
    "imgLocation": "Math Lab",
    "imgComment": "Add a small comment"
  },
  {
    "imgFileName": "math-lab-sample-img.png",
    "imgLocation": "Math Lab",
    "imgComment": "Add a small comment"
  },
  {
    "imgFileName": "math-lab-sample-img.png",
    "imgLocation": "Math Lab",
    "imgComment": "Add a small comment"
  },
  {
    "imgFileName": "math-lab-sample-img.png",
    "imgLocation": "Math Lab",
    "imgComment": "Add a small comment"
  }
]